pistonpy/__init__.py
pistonpy/exceptions.py
pistonpy/extensions.py
pistonpy/models.py
pistonpy/pistonapp.py
pistonpy/pistoncli.py
src/__init__.py
src/pistonapp.py
src/pistoncli.py
pistonpy-0.0.3.dist-info/LICENSE
pistonpy-0.0.3.dist-info/METADATA
pistonpy-0.0.3.dist-info/WHEEL
pistonpy-0.0.3.dist-info/top_level.txt
pistonpy-0.0.3.dist-info/RECORD
