Metadata-Version: 2.1
Name: pistonpy
Version: 0.0.3
Summary: An unofficial wrapper for Engineer Man's Piston API
Home-page: https://github.com/AaalbatrossGuy/pistonpy
Author: AalbatrossGuy
Author-email: thexcelsiorisback@gmail.com
License: UNKNOWN
Keywords: python,api-wrapper,piston,piston.py,code execution,run-code
Platform: UNKNOWN
Classifier: License :: OSI Approved :: MIT License
Classifier: Programming Language :: Python :: 3.8
Classifier: Programming Language :: Python :: 3.9
Classifier: Intended Audience :: Developers
Requires-Python: >=3.8
